topsis_dristi_102217188/__init__.py
topsis_dristi_102217188/topsis.py
Topsis_Dristi_102217188-1.0.0.dist-info/LICENSE
Topsis_Dristi_102217188-1.0.0.dist-info/METADATA
Topsis_Dristi_102217188-1.0.0.dist-info/WHEEL
Topsis_Dristi_102217188-1.0.0.dist-info/top_level.txt
Topsis_Dristi_102217188-1.0.0.dist-info/RECORD
